[
    {
        "title": "Xseane ⚖️",
        "subtitle": "Ben Stiller is helping refugees in #Syria .pic.twitter.com/4WTcZRUdOA",
        "url": "https://twitter.com/xseane/status/1211346318230245376",
        "_id": 1211346318230245376,
        "img": "https://pbs.twimg.com/media/EM-RDRFXYAAOjHr.jpg"
    },
    {
        "title": "Fayaz King",
        "subtitle": "In 2019, half of all refugees were children. \n\nDisplacement exposes children to forced marriage, forced labor, trafficking and recruitment into armed groups and gangs. Acceptance and access to education are key.\n\n2020 must be better #ForEveryChild. https://buff.ly/379zN9p pic.twitter.com/uUwqUKXTX5",
        "url": "https://twitter.com/fayaz_king/status/1210893240100151296",
        "_id": 1210893240100151296,
        "img": "https://pbs.twimg.com/media/EM30--cX0AEdd7T.jpg"
    },
    {
        "title": "🇺🇸 DR. CHI 🇳🇬",
        "subtitle": "People think the immigrants fleeing persecution at the border are Mexicans. Wrong!\n\nThe overwhelming majority of refugees are NOT #Mexican, but Central Americans from Guatemala, Nicaragua, and Honduras.\n\nMexicans are mainly leaving the USA not entering it.\n\nKnow your geography!pic.twitter.com/Fk1mARRFxv",
        "url": "https://twitter.com/chinyereosuji/status/1210765116624404482",
        "_id": 1210765116624404482,
        "img": "https://pbs.twimg.com/media/EM2AdAKVUAADyN2.jpg"
    },
    {
        "title": "(((Sultan-Caliph Abdallah of FIRE NAGY!!!🐪🇵🇸)))",
        "subtitle": "Eventually Israel began establishing Development Towns for the Mizrahi refugees. These were often Ma’abarots that turned into towns with the population provided permanent housing. These included Nazareth Illit and Or Yehuda pic.twitter.com/6tX0fTmfgj",
        "url": "https://twitter.com/abdallaha92/status/1210253006492573696",
        "_id": 1210253006492573696,
        "img": "https://pbs.twimg.com/media/EMuuppTWwAE1CIJ.png"
    },
    {
        "title": "W͙M͙I͙I͙I͙X͙",
        "subtitle": "#iWishChristmasWas less about virgin births and nativity scenes & more of a celebration refugees and immigrants. pic.twitter.com/Sw5WKzQsl5",
        "url": "https://twitter.com/WilliamMatt22/status/1209906696698486784",
        "_id": 1209906696698486784,
        "img": "https://pbs.twimg.com/media/EMpzufMU0AAEQer.jpg"
    },
    {
        "title": "Jesuit Refugee Service (JRS)/USA",
        "subtitle": "RT us: If YOU think that no matter where YOU live and what YOU do - there are ways YOU can respond to the needs of #refugees pic.twitter.com/UM0eHqaaWV",
        "url": "https://twitter.com/jrsusa/status/1212026241982910471",
        "_id": 1212026241982910471,
        "img": "https://pbs.twimg.com/media/ENH7cU3XsAEK0LZ.jpg"
    },
    {
        "title": "Quds News Network",
        "subtitle": "Palestinians in al-Fawwar refugee camp in the southern West Bank are once again in a new cycle of suffering after the Israeli army shut down with a metal bar the main entrance to the camp, today.  \n\nPhotos by Mash'hour Wahwah pic.twitter.com/HRxnfNIvC0",
        "url": "https://twitter.com/Qudsn_en/status/1212007356252524544",
        "_id": 1212007356252524544,
        "img": "https://pbs.twimg.com/media/ENHqQd7XsAEW2lB.jpg"
    },
    {
        "title": "Kokdamon #FollowBackHongKong",
        "subtitle": "I’ve draw many many birds on walls for the last 4 days, maybe more than 30? So beautiful to involved many kids and men from this refugees home to paint together birds of hope and freedom...\n\nA community art project by @cupofcolor_ngo\n#standwithhongkongpic.twitter.com/QK66GaoO3O",
        "url": "https://twitter.com/KokdamonLam/status/1211697402857578497",
        "_id": 1211697402857578497,
        "img": "https://pbs.twimg.com/media/ENDQW6RWsAIfbzS.jpg"
    },
    {
        "title": "👁‍🗨Z Crime News🇦🇺",
        "subtitle": "A Melbourne family has told how they were forced to spend 14 hours sitting at an airport boarding gate in a bureaucratic bungle which has highlighted confusion over how Australian permanent residents are dealt with at international borders.\n\n#refugees #asylumseekers #UNHCRpic.twitter.com/RRBNBqTzI0",
        "url": "https://twitter.com/ozcrimenews/status/1211618186266722304",
        "_id": 1211618186266722304,
        "img": "https://pbs.twimg.com/media/ENCIUDyVAAANuFx.jpg"
    },
    {
        "title": "Yusha Evans",
        "subtitle": "REFUGEE WINTER PACK APPEAL PLEASE DONATE NOW! http://yushaevans.com/2019/12/30/refugee-winter-pack-appeal-please-donate-now/ …pic.twitter.com/gMCf2vkfTP",
        "url": "https://twitter.com/yushaevans/status/1211609967649853440",
        "_id": 1211609967649853440,
        "img": "https://pbs.twimg.com/media/ENCA2D7W4AENaW5.jpg"
    },
    {
        "title": "Tamarack Resort",
        "subtitle": "Free Jeff Crosby & the Refugees show - Tonight, 7pm. pic.twitter.com/ZtNN4ihLrS",
        "url": "https://twitter.com/Ski_Tamarack/status/1211361771908321280",
        "_id": 1211361771908321280,
        "img": "https://pbs.twimg.com/media/EM-fHIsUwAA8BKr.jpg"
    },
    {
        "title": "SrStFrancisHolyCross",
        "subtitle": "On this #FeastoftheHolyFamily let us pray for all immigrants and refugees.  May the Holy Family keep them safe. pic.twitter.com/XGjLKzEmEl",
        "url": "https://twitter.com/gbfranciscans/status/1211255811525226496",
        "_id": 1211255811525226496,
        "img": "https://pbs.twimg.com/media/EM8-vd4XsAMja3E.jpg"
    },
    {
        "title": "Mike Smith",
        "subtitle": "City Beat: Pop-up shop helps get basic items to refugees. We could do the same for L.A.'s homeless people http://dlvr.it/RM5Snr pic.twitter.com/bgZ2zn7FYF",
        "url": "https://twitter.com/smithmike1980/status/1211211771832229888",
        "_id": 1211211771832229888,
        "img": "https://pbs.twimg.com/media/EM8WsAHU8AAmsqy.jpg"
    },
    {
        "title": "UNHCR Canada",
        "subtitle": "This holiday season, your gift can have a life-changing impact to refugees across the globe.\n\nVisit our online gift catalogue and give the gift of hope: https://trib.al/5tiZ0N0 pic.twitter.com/OJGLpqyY2O",
        "url": "https://twitter.com/UNHCRCanada/status/1211093383118229509",
        "_id": 1211093383118229509,
        "img": "https://pbs.twimg.com/media/EM6rA3_WsAcY6cp.jpg"
    },
    {
        "title": "FranklyMyDear",
        "subtitle": "Canada's Conservative Reform Party been confrontational and divisive for Canada since DAY 1 riding a Bigot Bus from Alberta to Ottawa only stopping periodically to stomp on Quebec flags. Since, their Intolerance Tent has only expanded to include gays, refugees, women's rights etc pic.twitter.com/4m23Dvxzvs",
        "url": "https://twitter.com/MrDash109/status/1211053732479340545",
        "_id": 1211053732479340545,
        "img": "https://pbs.twimg.com/media/EM6G8bBW4AAyvL2.jpg"
    },
    {
        "title": "Mary March",
        "subtitle": "For all those criticizing Pete, and claiming Jesus and his parents were NOT refugees, read Matthew 2: 13 please. pic.twitter.com/gmpSzUcZW7",
        "url": "https://twitter.com/MaryMarch3/status/1210603717940121600",
        "_id": 1210603717940121600,
        "img": "https://pbs.twimg.com/media/EMztqd4WoAASgMe.jpg"
    },
    {
        "title": "Nancy 🍑",
        "subtitle": "Same nativity scene without any Jews, Arabs, Africans or refugees. pic.twitter.com/qc45jbz1j3",
        "url": "https://twitter.com/BowmanNancy/status/1210438934230175746",
        "_id": 1210438934230175746,
        "img": "https://pbs.twimg.com/media/EMxXyu5XYAAO3L9.png"
    },
    {
        "title": "The immigration Coalition",
        "subtitle": "Jesus WAS a Refugee.\n\nJesus IS a Refugee. pic.twitter.com/Ko1lGEbTia",
        "url": "https://twitter.com/TheImmCoalition/status/1210285547354234881",
        "_id": 1210285547354234881,
        "img": "https://pbs.twimg.com/media/EMvMSX_XsAAceKc.jpg"
    },
    {
        "title": "(((Sultan-Caliph Abdallah of FIRE NAGY!!!🐪🇵🇸)))",
        "subtitle": "The Egyptian Jewish community continued to decrease. In 1967 there was another way of refugees and expellees, who lost their property following the 6 Day War. By the end there was only 2500 Jews left. pic.twitter.com/HqTZ6qaZR6",
        "url": "https://twitter.com/abdallaha92/status/1210248143293550592",
        "_id": 1210248143293550592,
        "img": "https://pbs.twimg.com/media/EMuqQ53WkAEpNc-.png"
    },
    {
        "title": "Millennial",
        "subtitle": "Pope Pius XII on the Holy Family, migrants, and refugees pic.twitter.com/jYtczEgaRN",
        "url": "https://twitter.com/MillennialJourn/status/1210212838620454912",
        "_id": 1210212838620454912,
        "img": "https://pbs.twimg.com/media/EMuKKLhXUAAtWVC.jpg"
    }
]