[
    {
        "text": "iraqi",
        "weight": 278
    },
    {
        "text": "standiraqi",
        "weight": 226
    },
    {
        "text": "asylum",
        "weight": 222
    },
    {
        "text": "resettlement",
        "weight": 207
    },
    {
        "text": "seekers",
        "weight": 203
    },
    {
        "text": "turkey",
        "weight": 176
    },
    {
        "text": "countries",
        "weight": 155
    },
    {
        "text": "years",
        "weight": 149
    },
    {
        "text": "waiting",
        "weight": 136
    },
    {
        "text": "children",
        "weight": 132
    },
    {
        "text": "world",
        "weight": 122
    },
    {
        "text": "help",
        "weight": 121
    },
    {
        "text": "long",
        "weight": 121
    },
    {
        "text": "people",
        "weight": 118
    },
    {
        "text": "host",
        "weight": 101
    },
    {
        "text": "please",
        "weight": 100
    },
    {
        "text": "suffering",
        "weight": 88
    },
    {
        "text": "rescue",
        "weight": 80
    },
    {
        "text": "solution",
        "weight": 74
    },
    {
        "text": "want",
        "weight": 71
    },
    {
        "text": "because",
        "weight": 68
    },
    {
        "text": "wait",
        "weight": 65
    },
    {
        "text": "like",
        "weight": 65
    },
    {
        "text": "support",
        "weight": 64
    },
    {
        "text": "country",
        "weight": 60
    },
    {
        "text": "migrants",
        "weight": 58
    },
    {
        "text": "legal",
        "weight": 57
    },
    {
        "text": "life",
        "weight": 57
    },
    {
        "text": "home",
        "weight": 54
    },
    {
        "text": "reach",
        "weight": 52
    },
    {
        "text": "lost",
        "weight": 51
    },
    {
        "text": "today",
        "weight": 50
    },
    {
        "text": "since",
        "weight": 49
    },
    {
        "text": "after",
        "weight": 49
    },
    {
        "text": "hope",
        "weight": 48
    },
    {
        "text": "time",
        "weight": 48
    },
    {
        "text": "europe",
        "weight": 48
    },
    {
        "text": "w",
        "weight": 45
    },
    {
        "text": "waited",
        "weight": 45
    },
    {
        "text": "live",
        "weight": 45
    },
    {
        "text": "rights",
        "weight": 45
    },
    {
        "text": "need",
        "weight": 45
    },
    {
        "text": "every",
        "weight": 44
    },
    {
        "text": "know",
        "weight": 42
    },
    {
        "text": "camp",
        "weight": 42
    },
    {
        "text": "t",
        "weight": 41
    },
    {
        "text": "family",
        "weight": 41
    },
    {
        "text": "human",
        "weight": 40
    },
    {
        "text": "syrian",
        "weight": 39
    },
    {
        "text": "some",
        "weight": 39
    },
    {
        "text": "make",
        "weight": 38
    },
    {
        "text": "year",
        "weight": 38
    },
    {
        "text": "last",
        "weight": 36
    },
    {
        "text": "future",
        "weight": 36
    },
    {
        "text": "welcome",
        "weight": 36
    },
    {
        "text": "work",
        "weight": 35
    },
    {
        "text": "safe",
        "weight": 35
    },
    {
        "text": "lives",
        "weight": 35
    },
    {
        "text": "whole",
        "weight": 34
    },
    {
        "text": "child",
        "weight": 33
    },
    {
        "text": "should",
        "weight": 33
    },
    {
        "text": "million",
        "weight": 33
    },
    {
        "text": "which",
        "weight": 33
    },
    {
        "text": "iraq",
        "weight": 33
    },
    {
        "text": "find",
        "weight": 33
    },
    {
        "text": "homeland",
        "weight": 33
    },
    {
        "text": "rohingya",
        "weight": 33
    },
    {
        "text": "government",
        "weight": 33
    },
    {
        "text": "over",
        "weight": 33
    },
    {
        "text": "files",
        "weight": 32
    },
    {
        "text": "humanitarian",
        "weight": 32
    },
    {
        "text": "women",
        "weight": 32
    },
    {
        "text": "left",
        "weight": 31
    },
    {
        "text": "syria",
        "weight": 31
    },
    {
        "text": "open",
        "weight": 31
    },
    {
        "text": "crisis",
        "weight": 31
    },
    {
        "text": "camps",
        "weight": 30
    },
    {
        "text": "during",
        "weight": 29
    },
    {
        "text": "became",
        "weight": 29
    },
    {
        "text": "victims",
        "weight": 28
    },
    {
        "text": "back",
        "weight": 28
    },
    {
        "text": "into",
        "weight": 28
    },
    {
        "text": "education",
        "weight": 28
    },
    {
        "text": "migration",
        "weight": 27
    },
    {
        "text": "could",
        "weight": 27
    },
    {
        "text": "right",
        "weight": 27
    },
    {
        "text": "stories",
        "weight": 26
    },
    {
        "text": "humanity",
        "weight": 26
    },
    {
        "text": "smugglers",
        "weight": 26
    },
    {
        "text": "living",
        "weight": 25
    },
    {
        "text": "made",
        "weight": 25
    },
    {
        "text": "great",
        "weight": 25
    },
    {
        "text": "illegal",
        "weight": 25
    },
    {
        "text": "crises",
        "weight": 25
    },
    {
        "text": "good",
        "weight": 24
    },
    {
        "text": "very",
        "weight": 24
    },
    {
        "text": "bangladesh",
        "weight": 23
    },
    {
        "text": "young",
        "weight": 23
    },
    {
        "text": "contact",
        "weight": 23
    },
    {
        "text": "hear",
        "weight": 23
    },
    {
        "text": "working",
        "weight": 23
    },
    {
        "text": "leave",
        "weight": 22
    },
    {
        "text": "read",
        "weight": 22
    },
    {
        "text": "take",
        "weight": 22
    },
    {
        "text": "nothing",
        "weight": 22
    },
    {
        "text": "k",
        "weight": 21
    },
    {
        "text": "still",
        "weight": 21
    },
    {
        "text": "families",
        "weight": 21
    },
    {
        "text": "unhcr",
        "weight": 21
    },
    {
        "text": "against",
        "weight": 21
    },
    {
        "text": "brexit",
        "weight": 21
    },
    {
        "text": "start",
        "weight": 20
    },
    {
        "text": "harsh",
        "weight": 20
    },
    {
        "text": "london",
        "weight": 20
    },
    {
        "text": "enough",
        "weight": 20
    },
    {
        "text": "group",
        "weight": 20
    },
    {
        "text": "climate",
        "weight": 19
    },
    {
        "text": "also",
        "weight": 19
    },
    {
        "text": "together",
        "weight": 19
    },
    {
        "text": "across",
        "weight": 19
    },
    {
        "text": "then",
        "weight": 19
    },
    {
        "text": "feel",
        "weight": 19
    },
    {
        "text": "think",
        "weight": 19
    },
    {
        "text": "email",
        "weight": 19
    },
    {
        "text": "community",
        "weight": 19
    },
    {
        "text": "international",
        "weight": 19
    },
    {
        "text": "greece",
        "weight": 19
    },
    {
        "text": "says",
        "weight": 18
    },
    {
        "text": "share",
        "weight": 18
    },
    {
        "text": "death",
        "weight": 18
    },
    {
        "text": "processing",
        "weight": 18
    },
    {
        "text": "fled",
        "weight": 18
    },
    {
        "text": "representative",
        "weight": 18
    },
    {
        "text": "resettle",
        "weight": 18
    },
    {
        "text": "forced",
        "weight": 18
    },
    {
        "text": "helping",
        "weight": 18
    },
    {
        "text": "before",
        "weight": 18
    },
    {
        "text": "part",
        "weight": 18
    },
    {
        "text": "solidarity",
        "weight": 18
    },
    {
        "text": "through",
        "weight": 18
    },
    {
        "text": "must",
        "weight": 18
    },
    {
        "text": "global",
        "weight": 18
    },
    {
        "text": "erdogan",
        "weight": 18
    },
    {
        "text": "came",
        "weight": 17
    },
    {
        "text": "everything",
        "weight": 17
    },
    {
        "text": "died",
        "weight": 17
    },
    {
        "text": "easy",
        "weight": 17
    },
    {
        "text": "leaving",
        "weight": 17
    },
    {
        "text": "other",
        "weight": 17
    },
    {
        "text": "reaching",
        "weight": 17
    },
    {
        "text": "feraszaman48yahoo",
        "weight": 17
    },
    {
        "text": "firas",
        "weight": 17
    },
    {
        "text": "alkhamees",
        "weight": 17
    },
    {
        "text": "school",
        "weight": 17
    },
    {
        "text": "mother",
        "weight": 17
    },
    {
        "text": "week",
        "weight": 16
    },
    {
        "text": "borders",
        "weight": 16
    },
    {
        "text": "escape",
        "weight": 16
    },
    {
        "text": "resettlment",
        "weight": 16
    },
    {
        "text": "3to6yrs",
        "weight": 16
    },
    {
        "text": "team",
        "weight": 16
    },
    {
        "text": "ways",
        "weight": 16
    },
    {
        "text": "ger",
        "weight": 16
    },
    {
        "text": "happy",
        "weight": 16
    },
    {
        "text": "stand",
        "weight": 16
    },
    {
        "text": "water",
        "weight": 15
    },
    {
        "text": "looking",
        "weight": 15
    },
    {
        "text": "dream",
        "weight": 15
    },
    {
        "text": "while",
        "weight": 15
    },
    {
        "text": "care",
        "weight": 15
    },
    {
        "text": "suffered",
        "weight": 15
    },
    {
        "text": "thing",
        "weight": 15
    },
    {
        "text": "schools",
        "weight": 15
    },
    {
        "text": "thousands",
        "weight": 15
    },
    {
        "text": "stranded",
        "weight": 15
    },
    {
        "text": "safely",
        "weight": 15
    },
    {
        "text": "much",
        "weight": 15
    },
    {
        "text": "best",
        "weight": 15
    },
    {
        "text": "seeking",
        "weight": 15
    },
    {
        "text": "deal",
        "weight": 15
    },
    {
        "text": "story",
        "weight": 14
    },
    {
        "text": "hundreds",
        "weight": 14
    },
    {
        "text": "first",
        "weight": 14
    },
    {
        "text": "safety",
        "weight": 14
    },
    {
        "text": "homeless",
        "weight": 14
    },
    {
        "text": "iranian",
        "weight": 14
    },
    {
        "text": "under",
        "weight": 14
    },
    {
        "text": "history",
        "weight": 14
    },
    {
        "text": "millions",
        "weight": 14
    },
    {
        "text": "losing",
        "weight": 14
    },
    {
        "text": "come",
        "weight": 14
    },
    {
        "text": "access",
        "weight": 14
    },
    {
        "text": "hands",
        "weight": 14
    },
    {
        "text": "arrived",
        "weight": 14
    },
    {
        "text": "book",
        "weight": 14
    },
    {
        "text": "friend",
        "weight": 14
    },
    {
        "text": "africa",
        "weight": 14
    },
    {
        "text": "govt",
        "weight": 14
    },
    {
        "text": "president",
        "weight": 14
    },
    {
        "text": "around",
        "weight": 13
    },
    {
        "text": "european",
        "weight": 13
    },
    {
        "text": "border",
        "weight": 13
    },
    {
        "text": "number",
        "weight": 13
    },
    {
        "text": "everyone",
        "weight": 13
    },
    {
        "text": "down",
        "weight": 13
    },
    {
        "text": "exhausted",
        "weight": 13
    },
    {
        "text": "save",
        "weight": 13
    },
    {
        "text": "give",
        "weight": 13
    },
    {
        "text": "fleeing",
        "weight": 13
    },
    {
        "text": "urgent",
        "weight": 13
    },
    {
        "text": "ever",
        "weight": 13
    },
    {
        "text": "hard",
        "weight": 13
    },
    {
        "text": "show",
        "weight": 13
    },
    {
        "text": "compacts",
        "weight": 13
    },
    {
        "text": "responsibility",
        "weight": 13
    },
    {
        "text": "2014",
        "weight": 13
    },
    {
        "text": "out",
        "weight": 13
    },
    {
        "text": "place",
        "weight": 13
    },
    {
        "text": "started",
        "weight": 13
    },
    {
        "text": "behind",
        "weight": 13
    },
    {
        "text": "making",
        "weight": 13
    },
    {
        "text": "compact",
        "weight": 13
    },
    {
        "text": "issues",
        "weight": 13
    },
    {
        "text": "iranianinturkey",
        "weight": 13
    },
    {
        "text": "change",
        "weight": 12
    },
    {
        "text": "report",
        "weight": 12
    },
    {
        "text": "keep",
        "weight": 12
    },
    {
        "text": "local",
        "weight": 12
    },
    {
        "text": "speed",
        "weight": 12
    },
    {
        "text": "forget",
        "weight": 12
    },
    {
        "text": "myanmar",
        "weight": 12
    },
    {
        "text": "voice",
        "weight": 12
    },
    {
        "text": "money",
        "weight": 12
    },
    {
        "text": "students",
        "weight": 12
    },
    {
        "text": "project",
        "weight": 12
    },
    {
        "text": "experience",
        "weight": 12
    },
    {
        "text": "health",
        "weight": 12
    },
    {
        "text": "componsate",
        "weight": 12
    },
    {
        "text": "look",
        "weight": 12
    },
    {
        "text": "unknown",
        "weight": 12
    },
    {
        "text": "freely",
        "weight": 12
    },
    {
        "text": "preys",
        "weight": 12
    },
    {
        "text": "hopeless",
        "weight": 12
    },
    {
        "text": "official",
        "weight": 12
    },
    {
        "text": "persecution",
        "weight": 12
    },
    {
        "text": "displaced",
        "weight": 12
    },
    {
        "text": "even",
        "weight": 12
    },
    {
        "text": "said",
        "weight": 12
    },
    {
        "text": "opportunity",
        "weight": 12
    },
    {
        "text": "taking",
        "weight": 12
    },
    {
        "text": "clear",
        "weight": 12
    },
    {
        "text": "hidden",
        "weight": 12
    },
    {
        "text": "united",
        "weight": 12
    },
    {
        "text": "delaram",
        "weight": 12
    },
    {
        "text": "2019",
        "weight": 11
    },
    {
        "text": "achieve",
        "weight": 11
    },
    {
        "text": "for3",
        "weight": 11
    },
    {
        "text": "huge",
        "weight": 11
    },
    {
        "text": "couldn",
        "weight": 11
    },
    {
        "text": "food",
        "weight": 11
    },
    {
        "text": "months",
        "weight": 11
    },
    {
        "text": "social",
        "weight": 11
    },
    {
        "text": "well",
        "weight": 11
    },
    {
        "text": "knows",
        "weight": 11
    },
    {
        "text": "eyes",
        "weight": 11
    },
    {
        "text": "does",
        "weight": 11
    },
    {
        "text": "calais",
        "weight": 11
    },
    {
        "text": "days",
        "weight": 11
    },
    {
        "text": "taken",
        "weight": 11
    },
    {
        "text": "morning",
        "weight": 11
    },
    {
        "text": "mobile",
        "weight": 11
    },
    {
        "text": "really",
        "weight": 11
    },
    {
        "text": "turkish",
        "weight": 11
    },
    {
        "text": "build",
        "weight": 11
    },
    {
        "text": "next",
        "weight": 11
    },
    {
        "text": "signing",
        "weight": 11
    },
    {
        "text": "news",
        "weight": 11
    },
    {
        "text": "harry",
        "weight": 11
    },
    {
        "text": "solutions",
        "weight": 11
    },
    {
        "text": "nationality",
        "weight": 11
    },
    {
        "text": "another",
        "weight": 10
    },
    {
        "text": "donations",
        "weight": 10
    },
    {
        "text": "largest",
        "weight": 10
    },
    {
        "text": "jewish",
        "weight": 10
    },
    {
        "text": "same",
        "weight": 10
    },
    {
        "text": "lived",
        "weight": 10
    },
    {
        "text": "callleaving",
        "weight": 10
    },
    {
        "text": "journy",
        "weight": 10
    },
    {
        "text": "stuck",
        "weight": 10
    },
    {
        "text": "twitter",
        "weight": 10
    },
    {
        "text": "person",
        "weight": 10
    },
    {
        "text": "flee",
        "weight": 10
    },
    {
        "text": "situation",
        "weight": 10
    },
    {
        "text": "didn",
        "weight": 10
    },
    {
        "text": "important",
        "weight": 10
    },
    {
        "text": "mass",
        "weight": 10
    },
    {
        "text": "journey",
        "weight": 10
    },
    {
        "text": "media",
        "weight": 10
    },
    {
        "text": "given",
        "weight": 10
    },
    {
        "text": "£",
        "weight": 10
    },
    {
        "text": "turn",
        "weight": 10
    },
    {
        "text": "watch",
        "weight": 10
    },
    {
        "text": "tell",
        "weight": 10
    },
    {
        "text": "different",
        "weight": 10
    },
    {
        "text": "skills",
        "weight": 10
    },
    {
        "text": "jordan",
        "weight": 10
    },
    {
        "text": "response",
        "weight": 10
    },
    {
        "text": "plan",
        "weight": 10
    },
    {
        "text": "policy",
        "weight": 10
    },
    {
        "text": "libya",
        "weight": 10
    },
    {
        "text": "university",
        "weight": 10
    },
    {
        "text": "forest",
        "weight": 10
    },
    {
        "text": "passedwhile",
        "weight": 10
    },
    {
        "text": "britain",
        "weight": 10
    },
    {
        "text": "risk",
        "weight": 10
    },
    {
        "text": "needs",
        "weight": 10
    },
    {
        "text": "lebanon",
        "weight": 10
    },
    {
        "text": "tomorrow",
        "weight": 9
    },
    {
        "text": "created",
        "weight": 9
    },
    {
        "text": "check",
        "weight": 9
    },
    {
        "text": "better",
        "weight": 9
    },
    {
        "text": "born",
        "weight": 9
    },
    {
        "text": "running",
        "weight": 9
    },
    {
        "text": "ks",
        "weight": 9
    },
    {
        "text": "having",
        "weight": 9
    },
    {
        "text": "mercy",
        "weight": 9
    },
    {
        "text": "efforts",
        "weight": 9
    },
    {
        "text": "supporting",
        "weight": 9
    },
    {
        "text": "wants",
        "weight": 9
    },
    {
        "text": "threat",
        "weight": 9
    },
    {
        "text": "never",
        "weight": 9
    },
    {
        "text": "minister",
        "weight": 9
    },
    {
        "text": "girls",
        "weight": 9
    },
    {
        "text": "sharing",
        "weight": 9
    },
    {
        "text": "immigrants",
        "weight": 9
    },
    {
        "text": "migrant",
        "weight": 9
    },
    {
        "text": "fair",
        "weight": 9
    },
    {
        "text": "groups",
        "weight": 9
    },
    {
        "text": "listen",
        "weight": 9
    },
    {
        "text": "asking",
        "weight": 9
    },
    {
        "text": "including",
        "weight": 9
    },
    {
        "text": "join",
        "weight": 9
    },
    {
        "text": "research",
        "weight": 9
    },
    {
        "text": "complete",
        "weight": 9
    },
    {
        "text": "turns",
        "weight": 9
    },
    {
        "text": "once",
        "weight": 9
    },
    {
        "text": "zone",
        "weight": 9
    },
    {
        "text": "chief",
        "weight": 9
    },
    {
        "text": "sent",
        "weight": 9
    },
    {
        "text": "”",
        "weight": 9
    },
    {
        "text": "such",
        "weight": 9
    },
    {
        "text": "coming",
        "weight": 9
    },
    {
        "text": "stop",
        "weight": 9
    },
    {
        "text": "full",
        "weight": 9
    },
    {
        "text": "ready",
        "weight": 9
    },
    {
        "text": "fire",
        "weight": 9
    },
    {
        "text": "standlraqi",
        "weight": 9
    },
    {
        "text": "party",
        "weight": 9
    },
    {
        "text": "services",
        "weight": 9
    },
    {
        "text": "vulnerable",
        "weight": 9
    },
    {
        "text": "green",
        "weight": 9
    },
    {
        "text": "delaramneedsacureasap",
        "weight": 9
    },
    {
        "text": "meet",
        "weight": 8
    },
    {
        "text": "jobs",
        "weight": 8
    },
    {
        "text": "again",
        "weight": 8
    },
    {
        "text": "parents",
        "weight": 8
    },
    {
        "text": "cause",
        "weight": 8
    },
    {
        "text": "helped",
        "weight": 8
    },
    {
        "text": "both",
        "weight": 8
    },
    {
        "text": "able",
        "weight": 8
    },
    {
        "text": "anyone",
        "weight": 8
    },
    {
        "text": "month",
        "weight": 8
    },
    {
        "text": "others",
        "weight": 8
    },
    {
        "text": "charity",
        "weight": 8
    },
    {
        "text": "five",
        "weight": 8
    },
    {
        "text": "believableacceptable",
        "weight": 8
    },
    {
        "text": "high",
        "weight": 8
    },
    {
        "text": "opportunities",
        "weight": 8
    },
    {
        "text": "learn",
        "weight": 8
    },
    {
        "text": "france",
        "weight": 8
    },
    {
        "text": "fight",
        "weight": 8
    },
    {
        "text": "deserve",
        "weight": 8
    },
    {
        "text": "enjoy",
        "weight": 8
    },
    {
        "text": "spent",
        "weight": 8
    },
    {
        "text": "faced",
        "weight": 8
    },
    {
        "text": "september",
        "weight": 8
    },
    {
        "text": "talk",
        "weight": 8
    },
    {
        "text": "‘",
        "weight": 8
    },
    {
        "text": "proud",
        "weight": 8
    },
    {
        "text": "means",
        "weight": 8
    },
    {
        "text": "amazing",
        "weight": 8
    },
    {
        "text": "communitysponsorship",
        "weight": 8
    },
    {
        "text": "members",
        "weight": 8
    },
    {
        "text": "doesn",
        "weight": 8
    },
    {
        "text": "west",
        "weight": 8
    },
    {
        "text": "free",
        "weight": 8
    },
    {
        "text": "needed",
        "weight": 8
    },
    {
        "text": "smith",
        "weight": 8
    },
    {
        "text": "benefits",
        "weight": 8
    },
    {
        "text": "trump",
        "weight": 8
    },
    {
        "text": "billion",
        "weight": 8
    },
    {
        "text": "lack",
        "weight": 8
    },
    {
        "text": "east",
        "weight": 8
    },
    {
        "text": "told",
        "weight": 8
    },
    {
        "text": "cannot",
        "weight": 8
    },
    {
        "text": "house",
        "weight": 8
    },
    {
        "text": "until",
        "weight": 8
    },
    {
        "text": "providing",
        "weight": 8
    },
    {
        "text": "measure",
        "weight": 8
    },
    {
        "text": "kids",
        "weight": 8
    },
    {
        "text": "legacy",
        "weight": 8
    },
    {
        "text": "states",
        "weight": 8
    },
    {
        "text": "british",
        "weight": 8
    },
    {
        "text": "issue",
        "weight": 8
    },
    {
        "text": "office",
        "weight": 8
    },
    {
        "text": "bike",
        "weight": 7
    },
    {
        "text": "according",
        "weight": 7
    },
    {
        "text": "conflict",
        "weight": 7
    },
    {
        "text": "love",
        "weight": 7
    },
    {
        "text": "exhibition",
        "weight": 7
    },
    {
        "text": "continue",
        "weight": 7
    },
    {
        "text": "solar",
        "weight": 7
    },
    {
        "text": "provide",
        "weight": 7
    },
    {
        "text": "business",
        "weight": 7
    },
    {
        "text": "national",
        "weight": 7
    },
    {
        "text": "german",
        "weight": 7
    },
    {
        "text": "always",
        "weight": 7
    },
    {
        "text": "civil",
        "weight": 7
    },
    {
        "text": "neither",
        "weight": 7
    },
    {
        "text": "arms",
        "weight": 7
    },
    {
        "text": "deliver",
        "weight": 7
    },
    {
        "text": "called",
        "weight": 7
    },
    {
        "text": "for3to6yrs",
        "weight": 7
    },
    {
        "text": "symbol",
        "weight": 7
    },
    {
        "text": "dreams",
        "weight": 7
    },
    {
        "text": "places",
        "weight": 7
    },
    {
        "text": "welcoming",
        "weight": 7
    },
    {
        "text": "inspiring",
        "weight": 7
    },
    {
        "text": "mark",
        "weight": 7
    },
    {
        "text": "conditions",
        "weight": 7
    },
    {
        "text": "supported",
        "weight": 7
    },
    {
        "text": "events",
        "weight": 7
    },
    {
        "text": "explain",
        "weight": 7
    },
    {
        "text": "return",
        "weight": 7
    },
    {
        "text": "excited",
        "weight": 7
    },
    {
        "text": "remember",
        "weight": 7
    },
    {
        "text": "peace",
        "weight": 7
    },
    {
        "text": "reading",
        "weight": 7
    },
    {
        "text": "iraqis",
        "weight": 7
    },
    {
        "text": "catastrophe",
        "weight": 7
    },
    {
        "text": "between",
        "weight": 7
    },
    {
        "text": "allow",
        "weight": 7
    },
    {
        "text": "greatest",
        "weight": 7
    },
    {
        "text": "settlement",
        "weight": 7
    },
    {
        "text": "friends",
        "weight": 7
    },
    {
        "text": "italy",
        "weight": 7
    },
    {
        "text": "communities",
        "weight": 7
    },
    {
        "text": "boys",
        "weight": 7
    },
    {
        "text": "wales",
        "weight": 7
    },
    {
        "text": "unless",
        "weight": 7
    },
    {
        "text": "training",
        "weight": 7
    },
    {
        "text": "programme",
        "weight": 7
    },
    {
        "text": "register",
        "weight": 7
    },
    {
        "text": "2011",
        "weight": 7
    },
    {
        "text": "holocaust",
        "weight": 7
    },
    {
        "text": "ling",
        "weight": 7
    },
    {
        "text": "move",
        "weight": 7
    },
    {
        "text": "danger",
        "weight": 7
    },
    {
        "text": "muslim",
        "weight": 7
    },
    {
        "text": "program",
        "weight": 7
    },
    {
        "text": "countryfile",
        "weight": 7
    },
    {
        "text": "foundation",
        "weight": 7
    },
    {
        "text": "name",
        "weight": 7
    },
    {
        "text": "past",
        "weight": 7
    },
    {
        "text": "leslie",
        "weight": 7
    },
    {
        "text": "greek",
        "weight": 7
    },
    {
        "text": "already",
        "weight": 7
    },
    {
        "text": "reunion",
        "weight": 7
    },
    {
        "text": "labour",
        "weight": 7
    },
    {
        "text": "island",
        "weight": 7
    },
    {
        "text": "recep",
        "weight": 7
    },
    {
        "text": "tayyip",
        "weight": 7
    },
    {
        "text": "miles",
        "weight": 7
    },
    {
        "text": "egypt",
        "weight": 7
    },
    {
        "text": "regions",
        "weight": 7
    },
    {
        "text": "joined",
        "weight": 7
    },
    {
        "text": "soon",
        "weight": 7
    },
    {
        "text": "gates",
        "weight": 7
    },
    {
        "text": "wars",
        "weight": 6
    },
    {
        "text": "merkel",
        "weight": 6
    },
    {
        "text": "worldwide",
        "weight": 6
    },
    {
        "text": "decision",
        "weight": 6
    },
    {
        "text": "kind",
        "weight": 6
    },
    {
        "text": "heart",
        "weight": 6
    },
    {
        "text": "palestinian",
        "weight": 6
    },
    {
        "text": "fear",
        "weight": 6
    },
    {
        "text": "desperation",
        "weight": 6
    },
    {
        "text": "going",
        "weight": 6
    },
    {
        "text": "racism",
        "weight": 6
    },
    {
        "text": "easily",
        "weight": 6
    },
    {
        "text": "become",
        "weight": 6
    },
    {
        "text": "closer",
        "weight": 6
    },
    {
        "text": "comes",
        "weight": 6
    },
    {
        "text": "lifejacket",
        "weight": 6
    },
    {
        "text": "salvation",
        "weight": 6
    },
    {
        "text": "pulling",
        "weight": 6
    },
    {
        "text": "homes",
        "weight": 6
    },
    {
        "text": "assistance",
        "weight": 6
    },
    {
        "text": "campaign",
        "weight": 6
    },
    {
        "text": "oppression",
        "weight": 6
    },
    {
        "text": "appeal",
        "weight": 6
    },
    {
        "text": "belgian",
        "weight": 6
    },
    {
        "text": "donate",
        "weight": 6
    },
    {
        "text": "weak",
        "weight": 6
    },
    {
        "text": "returned",
        "weight": 6
    },
    {
        "text": "treatment",
        "weight": 6
    },
    {
        "text": "loss",
        "weight": 6
    },
    {
        "text": "each",
        "weight": 6
    },
    {
        "text": "third",
        "weight": 6
    },
    {
        "text": "till",
        "weight": 6
    },
    {
        "text": "sanctuary",
        "weight": 6
    },
    {
        "text": "delaying",
        "weight": 6
    },
    {
        "text": "2013201420152016",
        "weight": 6
    },
    {
        "text": "behalf",
        "weight": 6
    },
    {
        "text": "potential",
        "weight": 6
    },
    {
        "text": "•",
        "weight": 6
    },
    {
        "text": "america",
        "weight": 6
    },
    {
        "text": "chance",
        "weight": 6
    },
    {
        "text": "glasgow",
        "weight": 6
    },
    {
        "text": "boat",
        "weight": 6
    },
    {
        "text": "syrians",
        "weight": 6
    },
    {
        "text": "small",
        "weight": 6
    },
    {
        "text": "outside",
        "weight": 6
    },
    {
        "text": "ensure",
        "weight": 6
    },
    {
        "text": "south",
        "weight": 6
    },
    {
        "text": "uganda",
        "weight": 6
    },
    {
        "text": "integration",
        "weight": 6
    },
    {
        "text": "raise",
        "weight": 6
    },
    {
        "text": "gave",
        "weight": 6
    },
    {
        "text": "streets",
        "weight": 6
    },
    {
        "text": "exist",
        "weight": 6
    },
    {
        "text": "train",
        "weight": 6
    },
    {
        "text": "area",
        "weight": 6
    },
    {
        "text": "legitimate",
        "weight": 6
    },
    {
        "text": "following",
        "weight": 6
    },
    {
        "text": "inside",
        "weight": 6
    },
    {
        "text": "english",
        "weight": 6
    },
    {
        "text": "victim",
        "weight": 6
    },
    {
        "text": "away",
        "weight": 6
    },
    {
        "text": "face",
        "weight": 6
    },
    {
        "text": "society",
        "weight": 6
    },
    {
        "text": "further",
        "weight": 6
    },
    {
        "text": "finish",
        "weight": 6
    },
    {
        "text": "terrorists",
        "weight": 6
    },
    {
        "text": "istanbul",
        "weight": 6
    },
    {
        "text": "burns",
        "weight": 6
    },
    {
        "text": "suffer",
        "weight": 6
    },
    {
        "text": "protection",
        "weight": 6
    },
    {
        "text": "refused",
        "weight": 6
    },
    {
        "text": "boris",
        "weight": 6
    },
    {
        "text": "used",
        "weight": 6
    },
    {
        "text": "saying",
        "weight": 6
    },
    {
        "text": "stay",
        "weight": 6
    },
    {
        "text": "latest",
        "weight": 6
    },
    {
        "text": "employment",
        "weight": 6
    },
    {
        "text": "n",
        "weight": 6
    },
    {
        "text": "forward",
        "weight": 6
    },
    {
        "text": "state",
        "weight": 6
    },
    {
        "text": "street",
        "weight": 6
    },
    {
        "text": "middle",
        "weight": 6
    },
    {
        "text": "promote",
        "weight": 6
    },
    {
        "text": "father",
        "weight": 6
    },
    {
        "text": "seen",
        "weight": 6
    },
    {
        "text": "someone",
        "weight": 6
    },
    {
        "text": "york",
        "weight": 6
    },
    {
        "text": "canada",
        "weight": 6
    },
    {
        "text": "ireland",
        "weight": 6
    },
    {
        "text": "retweet",
        "weight": 6
    },
    {
        "text": "scheme",
        "weight": 6
    },
    {
        "text": "thrive",
        "weight": 6
    },
    {
        "text": "benban",
        "weight": 6
    },
    {
        "text": "plant",
        "weight": 6
    },
    {
        "text": "winemakers",
        "weight": 6
    },
    {
        "text": "paradigm",
        "weight": 6
    },
    {
        "text": "breakers",
        "weight": 6
    },
    {
        "text": "unusual",
        "weight": 6
    },
    {
        "text": "entrepreneurs",
        "weight": 6
    },
    {
        "text": "ebrdstories",
        "weight": 6
    },
    {
        "text": "httpsstoriesebrd",
        "weight": 6
    },
    {
        "text": "release",
        "weight": 6
    },
    {
        "text": "resettled",
        "weight": 6
    },
    {
        "text": "tour",
        "weight": 6
    },
    {
        "text": "innocent",
        "weight": 6
    },
    {
        "text": "unhcrturkey",
        "weight": 6
    }
]